MANIFEST.in
README.rst
setup.py
docs/authors.rst
docs/contributing.rst
docs/history.rst
docs/index.rst
docs/installation.rst
docs/modules.rst
docs/readme.rst
docs/todo.rst
docs/usage.rst
docs/images/engine.0.png
docs/images/engine.1.png
docs/images/engine.2.png
docs/images/engine.3.png
docs/images/engine.4.png
docs/images/logo.png
docs/images/lvsrch.a.0.png
docs/images/nvhtml_struct_show.0.png
docs/images/nvhtml_struct_show.1.png
docs/images/pypi.png
docs/images/rdocs.png
nvhtml/__init__.py
nvhtml/bin.py
nvhtml/code_gen.py
nvhtml/consts.py
nvhtml/dmat_writer.py
nvhtml/engine.py
nvhtml/fs.py
nvhtml/htmldb.py
nvhtml/lvsrch.py
nvhtml/orb.py
nvhtml/rshtml.py
nvhtml/struct_show.py
nvhtml/txt.py
nvhtml/utils.py
nvhtml.egg-info/PKG-INFO
nvhtml.egg-info/SOURCES.txt
nvhtml.egg-info/dependency_links.txt
nvhtml.egg-info/entry_points.txt
nvhtml.egg-info/requires.txt
nvhtml.egg-info/top_level.txt
nvhtml/ATTRS/__init__.py
nvhtml/ATTRS/attrs.py
nvhtml/ATTRS/attrsrch.py
nvhtml/ATTRS/attrsrch.tst.py
nvhtml/ATTRS/code_gen.py
nvhtml/ATTRS/consts.py
nvhtml/ATTRS/eles.py
nvhtml/ATTRS/suffixes.py
nvhtml/ATTRS/txts.py
nvhtml/TAGS/__init__.py
nvhtml/TAGS/bin_nvhtml_tag.py
nvhtml/TAGS/bin_nvhtml_tgpth.py
nvhtml/WFS/__init__.py
nvhtml/WFS/bin_nvhtml_dir.py
nvhtml/WFS/bin_nvhtml_find_all.py
nvhtml/WFS/bin_nvhtml_html2rsh.py
nvhtml/WFS/bin_nvhtml_loc.py
nvhtml/WFS/bin_nvhtml_rsh2html.py
nvhtml/WFS/bin_nvhtml_sqlite.py
nvhtml/WFS/bin_nvhtml_struct_show.py
nvhtml/WFS/bin_nvhtml_wfs_dulrpls.py
nvhtml/WFS/bin_nvhtml_wfs_durlpls.py
nvhtml/WFS/bin_nvhtml_wfs_ifelpls.py
nvhtml/WFS/bin_nvhtml_wfs_json.py
nvhtml/WFS/bin_nvhtml_wfs_udlrpls.py
nvhtml/WFS/bin_nvrsh_struct_show.py