Metadata-Version: 1.1
Name: nvhtml
Version: 0.0.44
Summary: A Python library manipulate html
Home-page: https://github.com/ihgazni2/nvhtml
Author: dli
Author-email: 286264978@qq.com
License: MIT license
Keywords: html,tag,level,search
Platform: UNKNOWN
Classifier: Environment :: Console
Classifier: Environment :: Web Environment
Classifier: Intended Audience :: End Users/Desktop
Classifier: Intended Audience :: Developers
Classifier: Intended Audience :: System Administrators
Classifier: Programming Language :: Python :: 3
Classifier: Programming Language :: Python :: 3.3
Classifier: Programming Language :: Python :: 3.4
Classifier: Programming Language :: Python :: 3.5
Classifier: Programming Language :: Python :: 3.6
Classifier: Programming Language :: Python :: 3.7
